MANIFEST.in
requirements.txt
setup.py
test_requirements.txt
version.txt
cloudshell/__init__.py
cloudshell/networking/__init__.py
cloudshell/networking/brocade/__init__.py
cloudshell/networking/brocade/fastiron/__init__.py
cloudshell/networking/brocade/fastiron/fastiron_configuration.py
cloudshell/networking/brocade/fastiron/fastiron_resource_driver.py
cloudshell/networking/brocade/fastiron/autoload/__init__.py
cloudshell/networking/brocade/fastiron/autoload/brocade_fastiron_snmp_autoload.py
cloudshell/networking/brocade/fastiron/handler/__init__.py
cloudshell/networking/brocade/fastiron/handler/brocade_fastiron_configuration_operations.py
cloudshell/networking/brocade/fastiron/handler/brocade_fastiron_connectivity_operations.py
cloudshell/networking/brocade/fastiron/handler/brocade_fastiron_firmware_operations.py
cloudshell/networking/brocade/fastiron/mibs/FOUNDRY-SN-AGENT-MIB.py
cloudshell/networking/brocade/fastiron/mibs/FOUNDRY-SN-IP-MIB.py
cloudshell/networking/brocade/fastiron/mibs/FOUNDRY-SN-STACKING-MIB.py
cloudshell/networking/brocade/fastiron/mibs/FOUNDRY-SN-SWITCH-GROUP-MIB.py
cloudshell/networking/brocade/fastiron/mibs/HCNUM-TC.py
cloudshell/networking/brocade/fastiron/mibs/INET-ADDRESS-MIB.py
cloudshell/networking/brocade/fastiron/mibs/__init__.py
cloudshell_networking_brocade_fastiron.egg-info/PKG-INFO
cloudshell_networking_brocade_fastiron.egg-info/SOURCES.txt
cloudshell_networking_brocade_fastiron.egg-info/dependency_links.txt
cloudshell_networking_brocade_fastiron.egg-info/requires.txt
cloudshell_networking_brocade_fastiron.egg-info/top_level.txt