Metadata-Version: 1.0
Name: cloudshell-networking-brocade-fastiron
Version: 1.0.27
Summary: QualiSystems Brocade FastIron package
Home-page: http://www.qualisystems.com/
Author: QualiSystems
Author-email: info@qualisystems.com
License: UNKNOWN
Platform: UNKNOWN
